dpest/__init__.py
dpest/arguments.yml
dpest/functions.py
dpest/pst.py
dpest/utils/__init__.py
dpest/utils/facorig.py
dpest/utils/facparmax.py
dpest/utils/lsqr.py
dpest/utils/noptmax.py
dpest/utils/nphinored.py
dpest/utils/nphistp.py
dpest/utils/nrelpar.py
dpest/utils/numlam.py
dpest/utils/pestmode.py
dpest/utils/phiratsuf.py
dpest/utils/phiredlam.py
dpest/utils/phiredstp.py
dpest/utils/phiredswh.py
dpest/utils/relparmax.py
dpest/utils/relparstp.py
dpest/utils/rlambda1.py
dpest/utils/rlamfac.py
dpest/utils/rmv_lsqr.py
dpest/utils/rmv_splitcols.py
dpest/utils/rmv_svd.py
dpest/utils/rstfle.py
dpest/utils/svd.py
dpest/wheat/__init__.py
dpest/wheat/arguments.yml
dpest/wheat/overview.py
dpest/wheat/plantgro.py
dpest/wheat/ceres/__init__.py
dpest/wheat/ceres/arguments.yml
dpest/wheat/ceres/cul.py
dpest/wheat/ceres/eco.py
dpest/wheat/utils/__init__.py
dpest/wheat/utils/uplantgro.py
dpest-2.1.2.dist-info/licenses/LICENSE
dpest-2.1.2.dist-info/METADATA
dpest-2.1.2.dist-info/WHEEL
dpest-2.1.2.dist-info/top_level.txt
dpest-2.1.2.dist-info/RECORD
