Metadata-Version: 2.4
Name: dpest
Version: 2.1.2
Summary: A Python package for automating PEST (Parameter ESTimation) file creation for DSSAT crop model calibration using time series data. It generates template, instruction, and control files for parameter estimation, including tools for extending time series data.
Author-email: Luis Vargas Rojas <luisvargasrojas@gmail.com>
Project-URL: Homepage, https://github.com/DS4Ag/dpest
Project-URL: Issues, https://github.com/DS4Ag/dpest/issues
Classifier: Programming Language :: Python :: 3
Classifier: Operating System :: OS Independent
Classifier: License :: OSI Approved :: GNU General Public License v3 (GPLv3)
Requires-Python: >=3.7
License-File: LICENSE
Requires-Dist: pyemu>=1.3.8
Requires-Dist: pyyaml>=6.0.2
Requires-Dist: pandas>=2.2.3
Requires-Dist: matplotlib>=3.10.1
Requires-Dist: flopy>=3.9.2
Provides-Extra: dev
Requires-Dist: pytest>=8.4.0; extra == "dev"
Requires-Dist: coverage>=7.0.0; extra == "dev"
Requires-Dist: nbval; extra == "dev"
Requires-Dist: nbformat>=5.10.4; extra == "dev"
Requires-Dist: nbconvert>=7.16.0; extra == "dev"
Requires-Dist: ipykernel>=6.29.0; extra == "dev"
Provides-Extra: notebook
Requires-Dist: ipykernel>=6.29.0; extra == "notebook"
Requires-Dist: notebook>=7.1.0; extra == "notebook"
Requires-Dist: jupyter-client>=8.6.0; extra == "notebook"
Dynamic: license-file
Dynamic: requires-python
